README.rst
setup.py
binary_to_string/__init__.py
binary_to_string/base.py
binary_to_string.egg-info/PKG-INFO
binary_to_string.egg-info/SOURCES.txt
binary_to_string.egg-info/dependency_links.txt
binary_to_string.egg-info/requires.txt
binary_to_string.egg-info/top_level.txt