Metadata-Version: 1.0
Name: binary-to-string
Version: 0.1
Summary: This package transforms bytes into a string to integrate to a sklearn Pipeline
Home-page: UNKNOWN
Author: Mahmoud KOBBI
Author-email: mahmoud.kobbi@ibm.com
License: BSD 3
Platform: UNKNOWN
